typeless_dataclasses.py
typeless_dataclasses-1.0.dist-info/LICENSE
typeless_dataclasses-1.0.dist-info/METADATA
typeless_dataclasses-1.0.dist-info/WHEEL
typeless_dataclasses-1.0.dist-info/top_level.txt
typeless_dataclasses-1.0.dist-info/RECORD
