Metadata-Version: 2.1
Name: typeless-dataclasses
Version: 1.0
Summary: Use dataclasses without variable annotations.
Home-page: https://github.com/lemon24/typeless-dataclasses
Author: lemon24
License: UNKNOWN
Project-URL: Documentation, https://github.com/lemon24/typeless-dataclasses
Project-URL: Source Code, https://github.com/lemon24/typeless-dataclasses
Project-URL: Issue Tracker, https://github.com/lemon24/typeless-dataclasses/issues
Keywords: dataclasses,development
Platform: UNKNOWN
Classifier: Development Status :: 4 - Beta
Classifier: Intended Audience :: Developers
Classifier: License :: OSI Approved :: The Unlicense (Unlicense)
Classifier: Operating System :: OS Independent
Classifier: Programming Language :: Python :: 3
Classifier: Programming Language :: Python :: 3 :: Only
Classifier: Programming Language :: Python :: 3.6
Classifier: Programming Language :: Python :: 3.7
Classifier: Programming Language :: Python :: 3.8
Classifier: Programming Language :: Python :: 3.9
Classifier: Topic :: Software Development :: Libraries
Classifier: Topic :: Software Development :: Libraries :: Python Modules
Requires-Python: >=3.6
Provides-Extra: dev
Requires-Dist: twine ; extra == 'dev'
Requires-Dist: build ; extra == 'dev'
Requires-Dist: pre-commit ; extra == 'dev'
Requires-Dist: tox ; extra == 'dev'
Provides-Extra: tests
Requires-Dist: pytest ; extra == 'tests'
Requires-Dist: coverage ; extra == 'tests'
Requires-Dist: pytest-cov ; extra == 'tests'
Requires-Dist: dataclasses ; (python_version < "3.7") and extra == 'tests'
